rust_packer-1.1.4.dist-info/METADATA
rust_packer-1.1.4.dist-info/WHEEL
rust_packer-1.1.4.dist-info/licenses/LICENSE
rust_packer/__init__.py
rust_packer/rust_packer.cpython-312-darwin.so
rust_packer-1.1.4.dist-info/RECORD
