Metadata-Version: 2.4
Name: rust-packer
Version: 1.1.4
Requires-Dist: maturin>=1.9.3
Requires-Dist: numpy>=2.0
Requires-Dist: torch>=2.3
Requires-Dist: pytest>=8.4.1
Requires-Dist: coverage>=7.7.1
Requires-Dist: ruff>=0.11.2
Requires-Dist: taskipy>=1.14.1
License-File: LICENSE
Summary: Add your description here
Requires-Python: >=3.9
